{"log_id": 8011902262407323569, "direction": 0, "words_result_num": 13, "words_result": [{"probability": {"variance": 0.003326, "average": 0.923821, "min": 0.853023}, "location": {"width": 73, "top": 753, "height": 33, "left": 683}, "words": "5g袋"}, {"probability": {"variance": 0.0037, "average": 0.938636, "min": 0.877811}, "location": {"width": 92, "top": 750, "height": 28, "left": 1023}, "words": "不过"}, {"probability": {"variance": 0.002328, "average": 0.911141, "min": 0.855838}, "location": {"width": 157, "top": 942, "height": 28, "left": 956}, "words": "异常等中"}, {"probability": {"variance": 0.02995, "average": 0.826891, "min": 0.517317}, "location": {"width": 371, "top": 995, "height": 30, "left": 596}, "words": "青写过敏成青霉素房试良性"}, {"probability": {"variance": 0.030181, "average": 0.838873, "min": 0.597161}, "location": {"width": 101, "top": 1020, "height": 28, "left": 551}, "words": "注事项"}, {"probability": {"variance": 0, "average": 0.985945, "min": 0.985945}, "location": {"width": 73, "top": 1046, "height": 25, "left": 998}, "words": "生"}, {"probability": {"variance": 0, "average": 0.976934, "min": 0.976934}, "location": {"width": 25, "top": 1282, "height": 28, "left": 1335}, "words": "育"}, {"probability": {"variance": 0.036914, "average": 0.683346, "min": 0.385966}, "location": {"width": 452, "top": 1360, "height": 36, "left": 798}, "words": "量莫西,用后可能导过填"}, {"probability": {"variance": 0.049059, "average": 0.660964, "min": 0.384846}, "location": {"width": 191, "top": 1414, "height": 30, "left": 832}, "words": "曲小分泌再"}, {"probability": {"variance": 0.046506, "average": 0.561441, "min": 0.391268}, "location": {"width": 239, "top": 1414, "height": 28, "left": 1192}, "words": "血"}, {"probability": {"variance": 0.039046, "average": 0.75905, "min": 0.403056}, "location": {"width": 309, "top": 1465, "height": 33, "left": 764}, "words": "类精类种国环药物在"}, {"probability": {"variance": 0.03707, "average": 0.796713, "min": 0.604177}, "location": {"width": 562, "top": 1788, "height": 151, "left": 1113}, "words": "拼品"}, {"probability": {"variance": 0.057064, "average": 0.806944, "min": 0.36574}, "location": {"width": 756, "top": 2063, "height": 64, "left": 632}, "words": "琼海邦药股份有限公司中分公司"}], "language": -1}