{"log_id": 7192395275783875801, "direction": 0, "words_result_num": 28, "words_result": [{"probability": {"variance": 0, "average": 0.999656, "min": 0.999453}, "location": {"width": 100, "top": 139, "height": 27, "left": 178}, "words": "核准日期"}, {"probability": {"variance": 0, "average": 0.999688, "min": 0.99907}, "location": {"width": 100, "top": 184, "height": 29, "left": 178}, "words": "修改日期"}, {"probability": {"variance": 0.00355, "average": 0.954399, "min": 0.8344}, "location": {"width": 529, "top": 289, "height": 52, "left": 396}, "words": "硝苯地平缓释片(Ⅲ)说明书"}, {"probability": {"variance": 0, "average": 0.999238, "min": 0.99787}, "location": {"width": 412, "top": 356, "height": 31, "left": 455}, "words": "请仔细阅读说明书并在医师指导下使用"}, {"probability": {"variance": 0, "average": 0.999733, "min": 0.999201}, "location": {"width": 132, "top": 451, "height": 29, "left": 184}, "words": "【药品名称】"}, {"probability": {"variance": 0.000264, "average": 0.992617, "min": 0.941722}, "location": {"width": 335, "top": 497, "height": 31, "left": 235}, "words": "通用名称:硝苯地平缓释)"}, {"probability": {"variance": 0.006757, "average": 0.933016, "min": 0.776177}, "location": {"width": 516, "top": 546, "height": 28, "left": 235}, "words": "英文名称: Nifedipine Extended- -release Tablets)"}, {"probability": {"variance": 0.020479, "average": 0.924824, "min": 0.578129}, "location": {"width": 161, "top": 594, "height": 27, "left": 234}, "words": "汉语拼音:Xia"}, {"probability": {"variance": 0.003901, "average": 0.914898, "min": 0.824135}, "location": {"width": 221, "top": 593, "height": 30, "left": 455}, "words": " Iping Huanshi Pian(IID)"}, {"probability": {"variance": 6e-06, "average": 0.997595, "min": 0.993686}, "location": {"width": 83, "top": 639, "height": 29, "left": 183}, "words": "【成份】"}, {"probability": {"variance": 0.004229, "average": 0.975803, "min": 0.644457}, "location": {"width": 911, "top": 685, "height": 32, "left": 223}, "words": "本品主要成份为硝苯地平,其化学名称为2,6-二甲基-4(2-硝基苯基)-1,4-二氢-3,5"}, {"probability": {"variance": 6.7e-05, "average": 0.994449, "min": 0.974549}, "location": {"width": 194, "top": 733, "height": 28, "left": 176}, "words": "吡啶二甲酸二甲酯"}, {"probability": {"variance": 0, "average": 0.999814, "min": 0.999385}, "location": {"width": 128, "top": 780, "height": 26, "left": 222}, "words": "化学结构式"}, {"probability": {"variance": 0.031079, "average": 0.849516, "min": 0.602102}, "location": {"width": 136, "top": 851, "height": 65, "left": 815}, "words": "医药分"}, {"probability": {"variance": 0, "average": 0.481415, "min": 0.481415}, "location": {"width": 38, "top": 965, "height": 21, "left": 511}, "words": " HCO"}, {"probability": {"variance": 0.000344, "average": 0.980786, "min": 0.962252}, "location": {"width": 110, "top": 1016, "height": 46, "left": 504}, "words": "药销"}, {"probability": {"variance": 0, "average": 0.883727, "min": 0.883727}, "location": {"width": 43, "top": 1069, "height": 35, "left": 455}, "words": "从"}, {"probability": {"variance": 0.034713, "average": 0.895225, "min": 0.382177}, "location": {"width": 281, "top": 1103, "height": 38, "left": 217}, "words": "分子式:C17HgN2O6国"}, {"probability": {"variance": 0, "average": 0.904496, "min": 0.904496}, "location": {"width": 86, "top": 1077, "height": 88, "left": 516}, "words": "★"}, {"probability": {"variance": 0.000783, "average": 0.987167, "min": 0.906683}, "location": {"width": 163, "top": 1155, "height": 26, "left": 220}, "words": "分子量:346.34"}, {"probability": {"variance": 2.4e-05, "average": 0.993153, "min": 0.986738}, "location": {"width": 85, "top": 1200, "height": 32, "left": 178}, "words": "【性状"}, {"probability": {"variance": 0.01398, "average": 0.946948, "min": 0.622393}, "location": {"width": 391, "top": 1247, "height": 30, "left": 217}, "words": "体品为薄膜衣片,除去包衣后显黄色"}, {"probability": {"variance": 0.047232, "average": 0.734308, "min": 0.516979}, "location": {"width": 233, "top": 1266, "height": 74, "left": 226}, "words": "有公"}, {"probability": {"variance": 0, "average": 0.999444, "min": 0.998921}, "location": {"width": 110, "top": 1296, "height": 28, "left": 178}, "words": "【适应症"}, {"probability": {"variance": 0.000144, "average": 0.993375, "min": 0.969391}, "location": {"width": 114, "top": 1343, "height": 25, "left": 216}, "words": "1.高血压"}, {"probability": {"variance": 0.00042, "average": 0.989267, "min": 0.948309}, "location": {"width": 114, "top": 1389, "height": 27, "left": 215}, "words": "2.冠心病"}, {"probability": {"variance": 0.000688, "average": 0.990661, "min": 0.894087}, "location": {"width": 351, "top": 1437, "height": 28, "left": 252}, "words": "慢性稳定型心绞痛(劳累性心绞痛"}, {"probability": {"variance": 0, "average": 0.999416, "min": 0.998809}, "location": {"width": 84, "top": 1531, "height": 28, "left": 176}, "words": "【规格】"}], "language": 3}