{"log_id": 8905568460837766434, "direction": 0, "words_result_num": 56, "words_result": [{"probability": {"variance": 0.005855, "average": 0.970075, "min": 0.662072}, "location": {"width": 878, "top": 25, "height": 38, "left": 286}, "words": "血栓性不良事件、心肌梗塞和中风的风险增加,其风险可能是致命的。所有的 INSAIDS,包括COx-2选择性或非"}, {"probability": {"variance": 4e-06, "average": 0.999007, "min": 0.986327}, "location": {"width": 886, "top": 57, "height": 38, "left": 287}, "words": "选择性药物,可能有相似的风险。有心血管疾病或心血管疾病危险因素的患者,其风险更大。即使既往没有心"}, {"probability": {"variance": 0.000393, "average": 0.99532, "min": 0.862008}, "location": {"width": 876, "top": 90, "height": 35, "left": 289}, "words": "血管症状,医生和患者也应对此类事件的发生保持警惕。应告知患者严重心血管安全性的症状和/或体征以及"}, {"probability": {"variance": 1e-06, "average": 0.998718, "min": 0.996336}, "location": {"width": 190, "top": 130, "height": 26, "left": 290}, "words": "如果发生应采取的步骤"}, {"probability": {"variance": 6.5e-05, "average": 0.996599, "min": 0.948892}, "location": {"width": 847, "top": 153, "height": 36, "left": 328}, "words": "患者应该警惕诸如胸痛、气短、无力、言语含糊等症状和体征,而且当有任何上述症状或体征发生后应该"}, {"probability": {"variance": 1e-06, "average": 0.998861, "min": 0.99732}, "location": {"width": 154, "top": 194, "height": 27, "left": 290}, "words": "马上寻求医生帮助"}, {"probability": {"variance": 0.004204, "average": 0.984206, "min": 0.574331}, "location": {"width": 848, "top": 217, "height": 35, "left": 327}, "words": "5.和所有非甾体抗炎药( NSAIDS)一样,本品可导致新发高血压或使已有的高血压症状加重,其中的任何"}, {"probability": {"variance": 0.000674, "average": 0.992019, "min": 0.830059}, "location": {"width": 880, "top": 249, "height": 35, "left": 297}, "words": "一种都可导致心血管事件的发生率增加。服用噻嗪类或髓袢利尿剂的患者服用非甾体抗炎药( NSAIDS)时,可"}, {"probability": {"variance": 1.1e-05, "average": 0.99781, "min": 0.984876}, "location": {"width": 569, "top": 284, "height": 31, "left": 291}, "words": "能会影响这些药物的疗效。高血压病患者应慎用非甾体抗炎药( NSAID"}, {"probability": {"variance": 7e-06, "average": 0.998598, "min": 0.989524}, "location": {"width": 276, "top": 281, "height": 27, "left": 903}, "words": "包括本品。在开始本品治疗和整个"}, {"probability": {"variance": 0, "average": 0.999304, "min": 0.997692}, "location": {"width": 227, "top": 319, "height": 29, "left": 292}, "words": "治疗过程中应密切监测血压"}, {"probability": {"variance": 0.000636, "average": 0.989, "min": 0.895403}, "location": {"width": 554, "top": 347, "height": 33, "left": 327}, "words": "6.有高血压和/或心力衰竭(如液体潴留和水肿)病史的患者应慎用"}, {"probability": {"variance": 8.1e-05, "average": 0.995069, "min": 0.961854}, "location": {"width": 841, "top": 376, "height": 31, "left": 328}, "words": "7 NSAIDS,包括本品可能引起致命的、严重的皮肤不良反应,例如剥脱性皮炎、 Stevens Johnson综合征"}, {"probability": {"variance": 0.000752, "average": 0.987666, "min": 0.868546}, "location": {"width": 447, "top": 413, "height": 29, "left": 313}, "words": "SJS)和中毒性表皮坏死溶解症(TEN)。这些严重事件"}, {"probability": {"variance": 1.1e-05, "average": 0.997888, "min": 0.987309}, "location": {"width": 308, "top": 410, "height": 25, "left": 872}, "words": "的情况下出现。应告知患者严重皮肤反"}, {"probability": {"variance": 0.010843, "average": 0.972711, "min": 0.47716}, "location": {"width": 446, "top": 444, "height": 30, "left": 294}, "words": "应的症状和体征,在第一次出现皮肤皮疹或过敏反应的"}, {"probability": {"variance": 0.078103, "average": 0.737616, "min": 0.350351}, "location": {"width": 71, "top": 444, "height": 32, "left": 874}, "words": "本品"}, {"probability": {"variance": 0.002579, "average": 0.984006, "min": 0.808157}, "location": {"width": 245, "top": 479, "height": 24, "left": 322}, "words": "有胃肠道系统溃疡病史者慎用"}, {"probability": {"variance": 0.001037, "average": 0.99042, "min": 0.869991}, "location": {"width": 276, "top": 510, "height": 25, "left": 293}, "words": "9.心、肝、肾功能损害患者慎用"}, {"probability": {"variance": 0.003845, "average": 0.980375, "min": 0.655098}, "location": {"width": 634, "top": 537, "height": 29, "left": 295}, "words": "0.可以抑制血小板凝集,延长出血时间,故有出理间延长疾患的患者慎用"}, {"probability": {"variance": 0.000648, "average": 0.991139, "min": 0.880273}, "location": {"width": 635, "top": 569, "height": 31, "left": 294}, "words": "11.使用期间出现眩晕或其他中枢神经系统紊乱时应遥免驾驶车辆或操作机器"}, {"probability": {"variance": 0.000127, "average": 0.993989, "min": 0.953341}, "location": {"width": 428, "top": 602, "height": 30, "left": 297}, "words": "12.参阅双氯芬酸钠与对乙酰氨基酚项下的注意事项"}, {"probability": {"variance": 2e-06, "average": 0.999182, "min": 0.993645}, "location": {"width": 424, "top": 650, "height": 33, "left": 63}, "words": "【孕妇及哺乳期妇女用药】孕妇及哺乳期妇女禁用"}, {"probability": {"variance": 1.5e-05, "average": 0.997361, "min": 0.985817}, "location": {"width": 263, "top": 696, "height": 32, "left": 177}, "words": "【儿童用药】3岁以下小儿禁用"}, {"probability": {"variance": 1e-06, "average": 0.999094, "min": 0.996786}, "location": {"width": 235, "top": 744, "height": 28, "left": 176}, "words": "【老年用药】老年患者慎用"}, {"probability": {"variance": 0.00019, "average": 0.993981, "min": 0.936142}, "location": {"width": 1043, "top": 780, "height": 37, "left": 140}, "words": "【药物相互作用】1.双氯芬酸钠可使非甾体抗炎药的血药浓度升高。不宜与其他非甾体抗炎药同时长期使用。2.乙酰水杨酸可"}, {"probability": {"variance": 7e-06, "average": 0.998773, "min": 0.987023}, "location": {"width": 485, "top": 815, "height": 32, "left": 297}, "words": "降低双氯芬酸钠的血药浓度,并增加对乙酰氨基酚的肾毒性"}, {"probability": {"variance": 1.2e-05, "average": 0.998039, "min": 0.980855}, "location": {"width": 897, "top": 859, "height": 34, "left": 180}, "words": "【药物过量】逾量可出现双氯芬酸钠及乙酰氨基酚所至的肝毒性症状,应尽快给予护肝解毒药乙酰半胱氨酸等"}, {"probability": {"variance": 4e-05, "average": 0.997407, "min": 0.96413}, "location": {"width": 642, "top": 906, "height": 34, "left": 179}, "words": "【药理毒理】其中双氯芬酸钠为苯基乙酸衍生物,具有镇痛、抗炎、解热作用"}, {"probability": {"variance": 1.4e-05, "average": 0.997748, "min": 0.986044}, "location": {"width": 314, "top": 903, "height": 29, "left": 872}, "words": "作用比阿司匹林和吲哚美辛强,约为"}, {"probability": {"variance": 7.1e-05, "average": 0.997227, "min": 0.953545}, "location": {"width": 522, "top": 938, "height": 31, "left": 298}, "words": "阿司匹林的26~50倍,系外周型镇痛药。特点为药效强,不良反"}, {"probability": {"variance": 0.053204, "average": 0.844236, "min": 0.353491}, "location": {"width": 369, "top": 928, "height": 39, "left": 818}, "words": "三量,个体差异小。对乙酰氨基酚具"}, {"probability": {"variance": 0.001382, "average": 0.988522, "min": 0.820902}, "location": {"width": 889, "top": 964, "height": 36, "left": 297}, "words": "有良好的解热、镇痛作用。与阿司匹林比较,解热作用相痛作用较弱,证炎作用。两药具有协同作"}, {"probability": {"variance": 0, "average": 0.999902, "min": 0.999902}, "location": {"width": 22, "top": 1009, "height": 22, "left": 299}, "words": "用"}, {"probability": {"variance": 0, "average": 0.946847, "min": 0.946847}, "location": {"width": 34, "top": 1003, "height": 32, "left": 775}, "words": "E"}, {"probability": {"variance": 0.004085, "average": 0.984403, "min": 0.549593}, "location": {"width": 1029, "top": 1040, "height": 43, "left": 160}, "words": "【药代动力学】给药后吸收迅速,对乙酰氨基酚吸收后渗入全身体液,在肝谢,经肾脏排血浆半衰期为1~4小时,双"}, {"probability": {"variance": 0.000259, "average": 0.993169, "min": 0.93366}, "location": {"width": 768, "top": 1079, "height": 29, "left": 300}, "words": "氯芬酸钠吸收后与血浆蛋白的结合率达99%,经尿及胆汁排泄平均血降半期为1.2~1.8小时"}, {"probability": {"variance": 0.004207, "average": 0.975467, "min": 0.708278}, "location": {"width": 292, "top": 1129, "height": 27, "left": 222}, "words": "【贮藏】遮光,密闭保存(10~30℃)"}, {"probability": {"variance": 0.000259, "average": 0.992033, "min": 0.934592}, "location": {"width": 364, "top": 1173, "height": 29, "left": 218}, "words": "【包装】①无色安瓿。支2ml,每盒4支"}, {"probability": {"variance": 0.008598, "average": 0.965574, "min": 0.627828}, "location": {"width": 291, "top": 1204, "height": 26, "left": 301}, "words": "②无色安瓿。每支2ml,每盒10支"}, {"probability": {"variance": 0.000285, "average": 0.990758, "min": 0.930729}, "location": {"width": 274, "top": 1238, "height": 24, "left": 303}, "words": "③无色安瓿。每支2ml,每盒2支"}, {"probability": {"variance": 9.2e-05, "average": 0.99382, "min": 0.97379}, "location": {"width": 160, "top": 1284, "height": 26, "left": 201}, "words": "【有效期】36个月"}, {"probability": {"variance": 0.005153, "average": 0.956729, "min": 0.772452}, "location": {"width": 379, "top": 1323, "height": 35, "left": 180}, "words": "【执行标准】国家药品标准NS1-(X-132)-2"}, {"probability": {"variance": 0.003125, "average": 0.971233, "min": 0.791597}, "location": {"width": 278, "top": 1376, "height": 24, "left": 187}, "words": "【批准文号】国药准字H1990253"}, {"probability": {"variance": 1e-06, "average": 0.999128, "min": 0.996482}, "location": {"width": 226, "top": 1420, "height": 27, "left": 185}, "words": "【生产企业】【企业名称】"}, {"probability": {"variance": 1.3e-05, "average": 0.998239, "min": 0.986238}, "location": {"width": 245, "top": 1417, "height": 25, "left": 537}, "words": "广州白云山明兴制药有限公司"}, {"probability": {"variance": 0, "average": 0.999306, "min": 0.997996}, "location": {"width": 102, "top": 1466, "height": 23, "left": 310}, "words": "【生产地址】"}, {"probability": {"variance": 5e-06, "average": 0.998657, "min": 0.992234}, "location": {"width": 187, "top": 1463, "height": 24, "left": 538}, "words": "广州市工业大道北48号"}, {"probability": {"variance": 0, "average": 0.99933, "min": 0.998232}, "location": {"width": 99, "top": 1511, "height": 23, "left": 310}, "words": "【邮政编码】"}, {"probability": {"variance": 9.3e-05, "average": 0.991789, "min": 0.970783}, "location": {"width": 56, "top": 1512, "height": 19, "left": 544}, "words": "510250"}, {"probability": {"variance": 2e-06, "average": 0.99868, "min": 0.995999}, "location": {"width": 98, "top": 1559, "height": 22, "left": 312}, "words": "【电话号码】"}, {"probability": {"variance": 0.000859, "average": 0.983035, "min": 0.908902}, "location": {"width": 116, "top": 1557, "height": 20, "left": 565}, "words": "20)84307259"}, {"probability": {"variance": 0, "average": 0.999308, "min": 0.998472}, "location": {"width": 103, "top": 1602, "height": 25, "left": 309}, "words": "【传真号码】"}, {"probability": {"variance": 1.4e-05, "average": 0.996426, "min": 0.986751}, "location": {"width": 127, "top": 1603, "height": 19, "left": 554}, "words": "(020)84324723"}, {"probability": {"variance": 0, "average": 0.999185, "min": 0.998312}, "location": {"width": 66, "top": 1649, "height": 22, "left": 310}, "words": "【网址】"}, {"probability": {"variance": 0.01022, "average": 0.892481, "min": 0.757116}, "location": {"width": 42, "top": 1652, "height": 16, "left": 700}, "words": " om. cn"}], "language": 3}