{"log_id": 5293255723963725287, "direction": 0, "words_result_num": 30, "words_result": [{"probability": {"variance": 0.021652, "average": 0.623497, "min": 0.356548}, "location": {"width": 601, "top": 155, "height": 32, "left": 431}, "words": "用注射时可重里药"}, {"probability": {"variance": 0.049664, "average": 0.790171, "min": 0.351109}, "location": {"width": 551, "top": 443, "height": 34, "left": 339}, "words": "用对生无床试验建议用"}, {"probability": {"variance": 0.043275, "average": 0.775523, "min": 0.353968}, "location": {"width": 762, "top": 489, "height": 49, "left": 229}, "words": "家科麻已有价分的实验报告未见任何"}, {"probability": {"variance": 0.051283, "average": 0.716497, "min": 0.369991}, "location": {"width": 589, "top": 589, "height": 34, "left": 445}, "words": "时物的泌状未研根据大实验中血浓"}, {"probability": {"variance": 0.035015, "average": 0.752247, "min": 0.400681}, "location": {"width": 794, "top": 637, "height": 37, "left": 188}, "words": "估计幼白摄无基囊的装设在大类乳班斑位与大相"}, {"probability": {"variance": 0.049398, "average": 0.752363, "min": 0.379544}, "location": {"width": 674, "top": 686, "height": 34, "left": 186}, "words": "的婴儿所摄罗因妊时在子高中拔受的要低淘多"}, {"probability": {"variance": 0.036982, "average": 0.69315, "min": 0.464482}, "location": {"width": 345, "top": 736, "height": 34, "left": 195}, "words": "儿童用药本品月有前大资鞋"}, {"probability": {"variance": 0.056335, "average": 0.684053, "min": 0.363705}, "location": {"width": 476, "top": 786, "height": 34, "left": 147}, "words": "年患者用药法"}, {"probability": {"variance": 0.028861, "average": 0.837578, "min": 0.601199}, "location": {"width": 388, "top": 823, "height": 34, "left": 193}, "words": "药物相车作用"}, {"probability": {"variance": 0.021723, "average": 0.89734, "min": 0.415806}, "location": {"width": 505, "top": 876, "height": 30, "left": 231}, "words": "接受其麻药或与酰胶类结构大的药物治疗的病"}, {"probability": {"variance": 0.020271, "average": 0.893037, "min": 0.568147}, "location": {"width": 219, "top": 923, "height": 30, "left": 186}, "words": "寡性作用是可的"}, {"probability": {"variance": 1e-06, "average": 0.99887, "min": 0.998133}, "location": {"width": 196, "top": 976, "height": 32, "left": 205}, "words": "药物"}, {"probability": {"variance": 0.057083, "average": 0.738839, "min": 0.365242}, "location": {"width": 791, "top": 1024, "height": 47, "left": 236}, "words": "急性全身性毒外高麻药人流管产生海反应"}, {"probability": {"variance": 0.039565, "average": 0.867077, "min": 0.406843}, "location": {"width": 703, "top": 1070, "height": 34, "left": 184}, "words": "小时才达到血浆峰痘浓度这峰时间取玉射部位因此虫套症状会"}, {"probability": {"variance": 0.050218, "average": 0.730371, "min": 0.352143}, "location": {"width": 722, "top": 1118, "height": 35, "left": 166}, "words": "应雄包括中柜统心血管手统中神经系统毒是3"}, {"probability": {"variance": 0.072469, "average": 0.667648, "min": 0.350977}, "location": {"width": 270, "top": 1166, "height": 29, "left": 184}, "words": "出来先出的"}, {"probability": {"variance": 0.046862, "average": 0.61844, "min": 0.374337}, "location": {"width": 256, "top": 1162, "height": 34, "left": 597}, "words": "找好术头"}, {"probability": {"variance": 0.03771, "average": 0.755548, "min": 0.360218}, "location": {"width": 782, "top": 1193, "height": 66, "left": 183}, "words": "语言婚肌肉北新是报城的症能的先"}, {"probability": {"variance": 0.039706, "average": 0.861597, "min": 0.36104}, "location": {"width": 883, "top": 1253, "height": 42, "left": 183}, "words": "和神经官能症行为这些症状出现后会出现意识失和商大发作的惊时间"}, {"probability": {"variance": 0.018596, "average": 0.888826, "min": 0.519967}, "location": {"width": 810, "top": 1303, "height": 34, "left": 169}, "words": "钟至几分钟由千突引的肉活培加利时呼吸的影响立即产生快"}, {"probability": {"variance": 0.052775, "average": 0.758851, "min": 0.370789}, "location": {"width": 335, "top": 1349, "height": 34, "left": 183}, "words": "的症状在些博况一出"}, {"probability": {"variance": 0.048501, "average": 0.789518, "min": 0.515344}, "location": {"width": 217, "top": 1353, "height": 56, "left": 717}, "words": "加麻的性作"}, {"probability": {"variance": 0.028406, "average": 0.832117, "min": 0.460864}, "location": {"width": 267, "top": 1392, "height": 37, "left": 183}, "words": "中枢神经系统和优径"}, {"probability": {"variance": 0.043651, "average": 0.817618, "min": 0.41278}, "location": {"width": 364, "top": 1400, "height": 37, "left": 731}, "words": "来只要未注射大量的药物"}, {"probability": {"variance": 0.038388, "average": 0.902176, "min": 0.390535}, "location": {"width": 354, "top": 1445, "height": 29, "left": 183}, "words": "体就可以快得到恢复发生心机管"}, {"probability": {"variance": 0.009774, "average": 0.927233, "min": 0.647401}, "location": {"width": 347, "top": 1448, "height": 32, "left": 705}, "words": "全身高浓度局脉药会引起低血"}, {"probability": {"variance": 0.056662, "average": 0.743944, "min": 0.373543}, "location": {"width": 310, "top": 1493, "height": 27, "left": 184}, "words": "动过缓本失几"}, {"probability": {"variance": 0.030374, "average": 0.735041, "min": 0.490833}, "location": {"width": 239, "top": 1498, "height": 27, "left": 769}, "words": "因会起心胜钱果和心"}, {"probability": {"variance": 0.048284, "average": 0.693229, "min": 0.40018}, "location": {"width": 224, "top": 1541, "height": 29, "left": 765}, "words": "把比框神系"}, {"probability": {"variance": 0.040963, "average": 0.797466, "min": 0.478815}, "location": {"width": 238, "top": 1589, "height": 29, "left": 748}, "words": "如果出急性全身中的"}], "language": -1}