{"log_id": 4078017600621054885, "direction": 0, "words_result_num": 100, "words_result": [{"probability": {"variance": 0, "average": 0.999784, "min": 0.999763}, "location": {"width": 35, "top": 52, "height": 21, "left": 71}, "words": "核准"}, {"probability": {"variance": 0.018687, "average": 0.73948, "min": 0.602779}, "location": {"width": 37, "top": 51, "height": 43, "left": 111}, "words": "日期"}, {"probability": {"variance": 0.000122, "average": 0.992544, "min": 0.964622}, "location": {"width": 152, "top": 50, "height": 27, "left": 152}, "words": "2006年12月11日"}, {"probability": {"variance": 0, "average": 0.999961, "min": 0.999922}, "location": {"width": 33, "top": 75, "height": 17, "left": 72}, "words": "修改"}, {"probability": {"variance": 1e-06, "average": 0.999016, "min": 0.997353}, "location": {"width": 152, "top": 64, "height": 27, "left": 152}, "words": "2009年07月28日"}, {"probability": {"variance": 8e-06, "average": 0.998809, "min": 0.990429}, "location": {"width": 499, "top": 86, "height": 56, "left": 304}, "words": "丙戊酸钠缓释片说明书"}, {"probability": {"variance": 3e-06, "average": 0.998928, "min": 0.993403}, "location": {"width": 353, "top": 145, "height": 33, "left": 374}, "words": "请仔细阅读说明书并在医师指导下使用"}, {"probability": {"variance": 0, "average": 0.999984, "min": 0.999984}, "location": {"width": 19, "top": 206, "height": 18, "left": 74}, "words": "药"}, {"probability": {"variance": 0.002902, "average": 0.973846, "min": 0.853431}, "location": {"width": 80, "top": 221, "height": 20, "left": 102}, "words": "通用名称:丙"}, {"probability": {"variance": 0, "average": 0.999434, "min": 0.998731}, "location": {"width": 44, "top": 239, "height": 21, "left": 103}, "words": "商品名"}, {"probability": {"variance": 6e-06, "average": 0.997853, "min": 0.993792}, "location": {"width": 58, "top": 257, "height": 17, "left": 102}, "words": "英文名称"}, {"probability": {"variance": 0, "average": 0.999667, "min": 0.999458}, "location": {"width": 46, "top": 277, "height": 17, "left": 101}, "words": "汉语拼"}, {"probability": {"variance": 0.000585, "average": 0.981181, "min": 0.947014}, "location": {"width": 69, "top": 292, "height": 21, "left": 72}, "words": "【成份"}, {"probability": {"variance": 7e-06, "average": 0.997392, "min": 0.989934}, "location": {"width": 249, "top": 303, "height": 29, "left": 117}, "words": "品主要成份为丙戊酸钠。其化学名称为"}, {"probability": {"variance": 1e-06, "average": 0.999278, "min": 0.997951}, "location": {"width": 73, "top": 328, "height": 17, "left": 103}, "words": "其化学结构"}, {"probability": {"variance": 0.037811, "average": 0.839581, "min": 0.473853}, "location": {"width": 96, "top": 392, "height": 46, "left": 101}, "words": "分子:1620"}, {"probability": {"variance": 0.000276, "average": 0.986699, "min": 0.958631}, "location": {"width": 71, "top": 432, "height": 19, "left": 76}, "words": "【性状】"}, {"probability": {"variance": 0.00574, "average": 0.980585, "min": 0.641983}, "location": {"width": 304, "top": 441, "height": 26, "left": 105}, "words": "本品为薄膜衣片,除去包衣后显类白色至微黄色"}, {"probability": {"variance": 2.2e-05, "average": 0.992614, "min": 0.986353}, "location": {"width": 73, "top": 463, "height": 22, "left": 73}, "words": "【适应症"}, {"probability": {"variance": 0.000248, "average": 0.993028, "min": 0.954487}, "location": {"width": 99, "top": 481, "height": 19, "left": 106}, "words": "用于全身性、部"}, {"probability": {"variance": 3e-06, "average": 0.997997, "min": 0.994421}, "location": {"width": 149, "top": 473, "height": 19, "left": 420}, "words": "乳期妇女应用于严重病"}, {"probability": {"variance": 9.4e-05, "average": 0.994275, "min": 0.977447}, "location": {"width": 59, "top": 470, "height": 18, "left": 644}, "words": "其它药物"}, {"probability": {"variance": 4.3e-05, "average": 0.991076, "min": 0.981302}, "location": {"width": 73, "top": 495, "height": 20, "left": 76}, "words": "【规格】"}, {"probability": {"variance": 2e-06, "average": 0.997161, "min": 0.995099}, "location": {"width": 46, "top": 528, "height": 22, "left": 82}, "words": "用法用"}, {"probability": {"variance": 0.054487, "average": 0.731687, "min": 0.428}, "location": {"width": 107, "top": 506, "height": 44, "left": 421}, "words": "江办"}, {"probability": {"variance": 1e-06, "average": 0.999119, "min": 0.996017}, "location": {"width": 210, "top": 550, "height": 24, "left": 678}, "words": "最佳剂量需根据临床疗效来确定"}, {"probability": {"variance": 2e-06, "average": 0.99863, "min": 0.996145}, "location": {"width": 60, "top": 579, "height": 17, "left": 284}, "words": "要考虑做"}, {"probability": {"variance": 5e-06, "average": 0.997423, "min": 0.994432}, "location": {"width": 45, "top": 570, "height": 19, "left": 868}, "words": "在没有"}, {"probability": {"variance": 0, "average": 0.99973, "min": 0.999595}, "location": {"width": 44, "top": 594, "height": 17, "left": 300}, "words": "周内达"}, {"probability": {"variance": 8e-06, "average": 0.997572, "min": 0.99368}, "location": {"width": 52, "top": 585, "height": 19, "left": 853}, "words": "内达到"}, {"probability": {"variance": 2e-06, "average": 0.999047, "min": 0.996388}, "location": {"width": 79, "top": 601, "height": 18, "left": 840}, "words": "般剂量为20"}, {"probability": {"variance": 1.4e-05, "average": 0.997089, "min": 0.99174}, "location": {"width": 44, "top": 614, "height": 17, "left": 292}, "words": "痫药物"}, {"probability": {"variance": 0, "average": 0.999866, "min": 0.999866}, "location": {"width": 16, "top": 628, "height": 17, "left": 289}, "words": "进"}, {"probability": {"variance": 0.001479, "average": 0.983633, "min": 0.855001}, "location": {"width": 185, "top": 673, "height": 27, "left": 363}, "words": "临床意义不大,但要根据发作"}, {"probability": {"variance": 4.2e-05, "average": 0.993199, "min": 0.979981}, "location": {"width": 157, "top": 724, "height": 22, "left": 427}, "words": "最高危的病人(特别是接"}, {"probability": {"variance": 0, "average": 0.999995, "min": 0.999995}, "location": {"width": 15, "top": 722, "height": 18, "left": 674}, "words": "药"}, {"probability": {"variance": 0.079325, "average": 0.714943, "min": 0.433296}, "location": {"width": 29, "top": 719, "height": 19, "left": 785}, "words": "痫"}, {"probability": {"variance": 0, "average": 0.998961, "min": 0.998961}, "location": {"width": 15, "top": 719, "height": 18, "left": 890}, "words": "和"}, {"probability": {"variance": 0, "average": 0.884764, "min": 0.884764}, "location": {"width": 17, "top": 719, "height": 20, "left": 959}, "words": "的"}, {"probability": {"variance": 5e-06, "average": 0.99798, "min": 0.993627}, "location": {"width": 75, "top": 733, "height": 24, "left": 776}, "words": "进一步下降"}, {"probability": {"variance": 0, "average": 0.999114, "min": 0.99848}, "location": {"width": 30, "top": 749, "height": 17, "left": 166}, "words": "损害"}, {"probability": {"variance": 0.000145, "average": 0.994283, "min": 0.959947}, "location": {"width": 187, "top": 736, "height": 24, "left": 416}, "words": "化性疾病,3岁以后,危险性明"}, {"probability": {"variance": 0.000326, "average": 0.989493, "min": 0.958244}, "location": {"width": 50, "top": 739, "height": 17, "left": 637}, "words": "降,并随"}, {"probability": {"variance": 0.000968, "average": 0.98329, "min": 0.921133}, "location": {"width": 65, "top": 782, "height": 18, "left": 153}, "words": "状:临床症"}, {"probability": {"variance": 0, "average": 0.999731, "min": 0.999464}, "location": {"width": 45, "top": 775, "height": 19, "left": 518}, "words": "现下列"}, {"probability": {"variance": 0.000126, "average": 0.994006, "min": 0.962395}, "location": {"width": 168, "top": 770, "height": 23, "left": 604}, "words": "考虑到肝损害的可能,特别"}, {"probability": {"variance": 2e-06, "average": 0.998881, "min": 0.996422}, "location": {"width": 63, "top": 769, "height": 19, "left": 820}, "words": "高危病人"}, {"probability": {"variance": 0, "average": 0.99951, "min": 0.99951}, "location": {"width": 15, "top": 799, "height": 16, "left": 224}, "words": "通"}, {"probability": {"variance": 0, "average": 0.999879, "min": 0.999759}, "location": {"width": 41, "top": 790, "height": 17, "left": 604}, "words": "和腹痛"}, {"probability": {"variance": 1.7e-05, "average": 0.9979, "min": 0.988714}, "location": {"width": 85, "top": 804, "height": 19, "left": 652}, "words": "即进行临床检"}, {"probability": {"variance": 0.009681, "average": 0.94016, "min": 0.713685}, "location": {"width": 141, "top": 820, "height": 44, "left": 568}, "words": "缝特别是高危的病"}, {"probability": {"variance": 0, "average": 0.999332, "min": 0.998333}, "location": {"width": 134, "top": 818, "height": 24, "left": 833}, "words": "反映蛋白合成的试验"}, {"probability": {"variance": 0.000898, "average": 0.981696, "min": 0.929824}, "location": {"width": 59, "top": 817, "height": 22, "left": 974}, "words": "特别是凝"}, {"probability": {"variance": 0, "average": 0.999572, "min": 0.999572}, "location": {"width": 15, "top": 834, "height": 17, "left": 191}, "words": "前"}, {"probability": {"variance": 0, "average": 0.999247, "min": 0.999247}, "location": {"width": 16, "top": 833, "height": 16, "left": 280}, "words": "能"}, {"probability": {"variance": 7e-05, "average": 0.993532, "min": 0.977909}, "location": {"width": 80, "top": 834, "height": 20, "left": 938}, "words": "酶升高)需要"}, {"probability": {"variance": 1e-06, "average": 0.997681, "min": 0.996554}, "location": {"width": 78, "top": 847, "height": 17, "left": 217}, "words": "定在异常的"}, {"probability": {"variance": 1e-06, "average": 0.998496, "min": 0.997116}, "location": {"width": 56, "top": 839, "height": 17, "left": 637}, "words": "和凝血因"}, {"probability": {"variance": 0.003983, "average": 0.95531, "min": 0.866056}, "location": {"width": 42, "top": 838, "height": 18, "left": 752}, "words": "低,胆"}, {"probability": {"variance": 4e-06, "average": 0.998659, "min": 0.995407}, "location": {"width": 60, "top": 859, "height": 18, "left": 517}, "words": "物的代谢"}, {"probability": {"variance": 0.048966, "average": 0.881689, "min": 0.391075}, "location": {"width": 81, "top": 880, "height": 19, "left": 355}, "words": "间,少数患"}, {"probability": {"variance": 3e-05, "average": 0.997114, "min": 0.980684}, "location": {"width": 143, "top": 872, "height": 20, "left": 734}, "words": "治疗时,可单独出现或"}, {"probability": {"variance": 1e-06, "average": 0.998648, "min": 0.997408}, "location": {"width": 58, "top": 901, "height": 18, "left": 83}, "words": "量减少或"}, {"probability": {"variance": 0, "average": 0.998867, "min": 0.998867}, "location": {"width": 16, "top": 917, "height": 20, "left": 142}, "words": "消"}, {"probability": {"variance": 0, "average": 0.99944, "min": 0.999193}, "location": {"width": 32, "top": 909, "height": 16, "left": 588}, "words": "通常"}, {"probability": {"variance": 0, "average": 0.999806, "min": 0.999806}, "location": {"width": 15, "top": 940, "height": 17, "left": 603}, "words": "多"}, {"probability": {"variance": 0, "average": 0.97929, "min": 0.97929}, "location": {"width": 17, "top": 938, "height": 18, "left": 967}, "words": "用"}, {"probability": {"variance": 2e-06, "average": 0.998604, "min": 0.9965}, "location": {"width": 58, "top": 1014, "height": 18, "left": 216}, "words": "常的单纯"}, {"probability": {"variance": 1e-05, "average": 0.998273, "min": 0.987192}, "location": {"width": 205, "top": 1008, "height": 21, "left": 351}, "words": "血症时有出现,但不需要停止治"}, {"probability": {"variance": 4.4e-05, "average": 0.996472, "min": 0.983274}, "location": {"width": 65, "top": 1033, "height": 18, "left": 204}, "words": "重增加,闭"}, {"probability": {"variance": 0.001696, "average": 0.983229, "min": 0.874272}, "location": {"width": 114, "top": 1044, "height": 22, "left": 302}, "words": "听力丧失,但其因"}, {"probability": {"variance": 0, "average": 0.998762, "min": 0.998762}, "location": {"width": 14, "top": 1066, "height": 16, "left": 218}, "words": "起"}, {"probability": {"variance": 0.000113, "average": 0.993287, "min": 0.972278}, "location": {"width": 65, "top": 1056, "height": 18, "left": 679}, "words": "综合征,多"}, {"probability": {"variance": 0, "average": 0.999692, "min": 0.999669}, "location": {"width": 30, "top": 1054, "height": 19, "left": 834}, "words": "报导"}, {"probability": {"variance": 0.000616, "average": 0.982456, "min": 0.939993}, "location": {"width": 50, "top": 1075, "height": 21, "left": 497}, "words": "合征,但"}, {"probability": {"variance": 0, "average": 0.999059, "min": 0.999059}, "location": {"width": 14, "top": 1115, "height": 17, "left": 262}, "words": "个"}, {"probability": {"variance": 0.002267, "average": 0.987522, "min": 0.797073}, "location": {"width": 247, "top": 1109, "height": 24, "left": 322}, "words": "族有严重肝炎史,特别是药物所致肝炎"}, {"probability": {"variance": 2e-06, "average": 0.998461, "min": 0.996354}, "location": {"width": 102, "top": 1179, "height": 23, "left": 292}, "words": "丙戊酸治疗时伴"}, {"probability": {"variance": 4e-06, "average": 0.997701, "min": 0.9958}, "location": {"width": 30, "top": 1178, "height": 18, "left": 469}, "words": "险如"}, {"probability": {"variance": 1.8e-05, "average": 0.995506, "min": 0.991247}, "location": {"width": 37, "top": 1198, "height": 18, "left": 300}, "words": "的危"}, {"probability": {"variance": 8e-06, "average": 0.996192, "min": 0.988944}, "location": {"width": 137, "top": 1215, "height": 21, "left": 292}, "words": "生下的婴儿畸形的总"}, {"probability": {"variance": 0.000327, "average": 0.985132, "min": 0.952475}, "location": {"width": 111, "top": 1208, "height": 22, "left": 561}, "words": "般孕妇的(3%)的"}, {"probability": {"variance": 0, "average": 0.999381, "min": 0.999313}, "location": {"width": 41, "top": 1237, "height": 18, "left": 85}, "words": "是与"}, {"probability": {"variance": 0.000783, "average": 0.976689, "min": 0.92839}, "location": {"width": 48, "top": 1252, "height": 17, "left": 118}, "words": "(2)伴随"}, {"probability": {"variance": 1e-06, "average": 0.997361, "min": 0.996357}, "location": {"width": 32, "top": 1267, "height": 18, "left": 119}, "words": "在动"}, {"probability": {"variance": 0.026583, "average": 0.937912, "min": 0.476996}, "location": {"width": 127, "top": 1263, "height": 22, "left": 309}, "words": "兔有致畸胎作用,在"}, {"probability": {"variance": 1e-06, "average": 0.99872, "min": 0.997025}, "location": {"width": 71, "top": 1258, "height": 19, "left": 645}, "words": "在怀孕期前"}, {"probability": {"variance": 7.4e-05, "average": 0.992316, "min": 0.973671}, "location": {"width": 80, "top": 1274, "height": 17, "left": 642}, "words": "的倾向:脊髓"}, {"probability": {"variance": 0, "average": 0.999699, "min": 0.99943}, "location": {"width": 28, "top": 1273, "height": 17, "left": 792}, "words": "脊柱"}, {"probability": {"variance": 5e-06, "average": 0.997023, "min": 0.994113}, "location": {"width": 75, "top": 1287, "height": 17, "left": 88}, "words": "已有报告面"}, {"probability": {"variance": 0, "average": 0.999756, "min": 0.999756}, "location": {"width": 15, "top": 1337, "height": 15, "left": 133}, "words": "如"}, {"probability": {"variance": 0.020815, "average": 0.906146, "min": 0.458461}, "location": {"width": 303, "top": 1327, "height": 38, "left": 419}, "words": "停,建革药,应使用每日最小有效剂量"}, {"probability": {"variance": 0.000158, "average": 0.995002, "min": 0.955693}, "location": {"width": 159, "top": 1336, "height": 20, "left": 898}, "words": "血或其它畸形,应进行特"}, {"probability": {"variance": 5e-06, "average": 0.997562, "min": 0.994386}, "location": {"width": 74, "top": 1370, "height": 18, "left": 88}, "words": "殊的产前检"}, {"probability": {"variance": 0.001333, "average": 0.983929, "min": 0.868141}, "location": {"width": 346, "top": 1393, "height": 27, "left": 238}, "words": "用丙戊酸钠,新生儿出现出血综合征,出血综合征与血纤"}, {"probability": {"variance": 8e-06, "average": 0.997598, "min": 0.992633}, "location": {"width": 121, "top": 1392, "height": 19, "left": 651}, "words": "有关这种综合征要"}, {"probability": {"variance": 0.001288, "average": 0.988193, "min": 0.849802}, "location": {"width": 226, "top": 1387, "height": 21, "left": 832}, "words": "依赖因子减少鉴别,后者是由苯巴比"}, {"probability": {"variance": 1e-06, "average": 0.999286, "min": 0.997148}, "location": {"width": 87, "top": 1420, "height": 18, "left": 90}, "words": "妥和酶诱导剂"}, {"probability": {"variance": 0.000228, "average": 0.994168, "min": 0.951514}, "location": {"width": 126, "top": 1431, "height": 20, "left": 261}, "words": "是低下的,大约是母"}, {"probability": {"variance": 0.00046, "average": 0.986312, "min": 0.922009}, "location": {"width": 207, "top": 1426, "height": 23, "left": 443}, "words": "平的1%~10%,至今,新生儿期母孚"}], "language": 3}