{"log_id": 7296057099587757462, "direction": 0, "words_result_num": 50, "words_result": [{"probability": {"variance": 0.002223, "average": 0.986285, "min": 0.71835}, "location": {"width": 685, "top": 62, "height": 19, "left": 51}, "words": "3、正常人体血液的渗透压摩尔浓度范围为285~310 mosmol/kg,本品的渗透压摩尔浓度范围"}, {"probability": {"variance": 0.002337, "average": 0.951656, "min": 0.903311}, "location": {"width": 152, "top": 83, "height": 15, "left": 20}, "words": " 260-320mosmol/kg"}, {"probability": {"variance": 0.003001, "average": 0.983652, "min": 0.676649}, "location": {"width": 562, "top": 99, "height": 17, "left": 53}, "words": "4、使用前请认真检查,如存在药液浑浊或有异物、瓶身/袋体破损或渗漏等情况切勿使用"}, {"probability": {"variance": 6.8e-05, "average": 0.996427, "min": 0.971897}, "location": {"width": 151, "top": 118, "height": 17, "left": 24}, "words": "孕妇及哺乳期妇女用药"}, {"probability": {"variance": 1.4e-05, "average": 0.997883, "min": 0.986925}, "location": {"width": 148, "top": 135, "height": 17, "left": 53}, "words": "妊娠高血压综合征禁用"}, {"probability": {"variance": 9e-06, "average": 0.997141, "min": 0.992151}, "location": {"width": 67, "top": 154, "height": 17, "left": 21}, "words": "儿童用药"}, {"probability": {"variance": 2e-06, "average": 0.998417, "min": 0.995542}, "location": {"width": 163, "top": 172, "height": 16, "left": 54}, "words": "补液量和速度应严格控制"}, {"probability": {"variance": 0.00173, "average": 0.976591, "min": 0.893514}, "location": {"width": 66, "top": 190, "height": 16, "left": 20}, "words": "[老年用药"}, {"probability": {"variance": 5e-06, "average": 0.998473, "min": 0.991956}, "location": {"width": 164, "top": 207, "height": 17, "left": 53}, "words": "补液量和速度应严格控制"}, {"probability": {"variance": 0.000855, "average": 0.980145, "min": 0.908506}, "location": {"width": 99, "top": 227, "height": 16, "left": 23}, "words": "[药物相互作用]"}, {"probability": {"variance": 1.8e-05, "average": 0.998315, "min": 0.979682}, "location": {"width": 353, "top": 244, "height": 16, "left": 54}, "words": "作为药物溶剂或稀释剂时,应注意药物之间的配伍禁忌"}, {"probability": {"variance": 1e-05, "average": 0.997012, "min": 0.991006}, "location": {"width": 63, "top": 262, "height": 17, "left": 23}, "words": "[药物过量"}, {"probability": {"variance": 0.003211, "average": 0.986942, "min": 0.727321}, "location": {"width": 325, "top": 279, "height": 17, "left": 54}, "words": "可致高钠血症和低钾血症,并能引起碳酸氢盐丢失"}, {"probability": {"variance": 0.001183, "average": 0.981773, "min": 0.913004}, "location": {"width": 62, "top": 298, "height": 17, "left": 23}, "words": "[药理毒理"}, {"probability": {"variance": 0.000194, "average": 0.99548, "min": 0.91155}, "location": {"width": 682, "top": 314, "height": 18, "left": 54}, "words": "氯化钠是一种电解质补充药物。钠和氯是机体重要的电解质,主要存在于细胞外液,对维持正常的血液和"}, {"probability": {"variance": 0.002256, "average": 0.988469, "min": 0.719933}, "location": {"width": 702, "top": 332, "height": 17, "left": 20}, "words": "细胞外液的容量和渗透压起着非常重要的作用。正常血清钠浓度为135~145mmol/L,占血浆阳离子的92%"}, {"probability": {"variance": 0.002613, "average": 0.987819, "min": 0.630412}, "location": {"width": 716, "top": 350, "height": 17, "left": 20}, "words": "总渗透压的90%,故血浆钠量对渗透压起着决定性作用。正常血清氯浓度为98~106mmol/L人体中钠、氯"}, {"probability": {"variance": 0.000137, "average": 0.995414, "min": 0.9429}, "location": {"width": 516, "top": 367, "height": 17, "left": 20}, "words": "离子主要通过下丘脑、垂体后叶和肾脏进行调节,维持体液容量和渗透压的稳定"}, {"probability": {"variance": 2e-06, "average": 0.997411, "min": 0.995239}, "location": {"width": 77, "top": 386, "height": 17, "left": 24}, "words": "药代动力学"}, {"probability": {"variance": 0.000525, "average": 0.991891, "min": 0.885762}, "location": {"width": 681, "top": 402, "height": 18, "left": 55}, "words": "氯化钠静脉注射后直接进入血液循环,在体内广泛分布,但主要存在于细胞外液。钠离子、氯离子均可被"}, {"probability": {"variance": 0.000362, "average": 0.993401, "min": 0.907344}, "location": {"width": 486, "top": 420, "height": 18, "left": 21}, "words": "肾小球滤过,并部分被肾小管重吸收。由肾脏随尿排泄,仅少部分从汗排出"}, {"probability": {"variance": 0.000487, "average": 0.984735, "min": 0.932294}, "location": {"width": 95, "top": 440, "height": 15, "left": 24}, "words": "[贮藏]密闭保存"}, {"probability": {"variance": 0.003786, "average": 0.963215, "min": 0.749091}, "location": {"width": 234, "top": 457, "height": 18, "left": 20}, "words": "[包装][有效期][执行标准]批准文号"}, {"probability": {"variance": 6e-06, "average": 0.997471, "min": 0.994975}, "location": {"width": 48, "top": 484, "height": 16, "left": 94}, "words": "包装"}, {"probability": {"variance": 1e-06, "average": 0.998589, "min": 0.997226}, "location": {"width": 48, "top": 482, "height": 17, "left": 315}, "words": "有效期"}, {"probability": {"variance": 5e-05, "average": 0.995192, "min": 0.982977}, "location": {"width": 80, "top": 481, "height": 18, "left": 436}, "words": "执行标准"}, {"probability": {"variance": 0.000239, "average": 0.990696, "min": 0.96395}, "location": {"width": 63, "top": 480, "height": 17, "left": 610}, "words": "批准文号"}, {"probability": {"variance": 6.1e-05, "average": 0.994108, "min": 0.973345}, "location": {"width": 158, "top": 512, "height": 14, "left": 32}, "words": "聚丙烯输液瓶装,每瓶250m"}, {"probability": {"variance": 4e-06, "average": 0.998122, "min": 0.994667}, "location": {"width": 39, "top": 517, "height": 14, "left": 320}, "words": "24个月"}, {"probability": {"variance": 0.000171, "average": 0.994602, "min": 0.952805}, "location": {"width": 125, "top": 517, "height": 14, "left": 425}, "words": "《中国药典》2015年版"}, {"probability": {"variance": 0.000223, "average": 0.991251, "min": 0.941158}, "location": {"width": 112, "top": 517, "height": 14, "left": 591}, "words": "国药准字H20054022"}, {"probability": {"variance": 0.000569, "average": 0.990599, "min": 0.892986}, "location": {"width": 211, "top": 527, "height": 14, "left": 32}, "words": "聚丙烯输液瓶装(双阀),每瓶250ml"}, {"probability": {"variance": 5.3e-05, "average": 0.996687, "min": 0.968548}, "location": {"width": 193, "top": 554, "height": 13, "left": 32}, "words": "直立式聚丙烯输液袋装,每袋250m"}, {"probability": {"variance": 0.000419, "average": 0.989815, "min": 0.928516}, "location": {"width": 248, "top": 568, "height": 15, "left": 32}, "words": "直立式聚丙烯输液袋装《双阀),每袋250ml"}, {"probability": {"variance": 4e-06, "average": 0.998096, "min": 0.994538}, "location": {"width": 39, "top": 560, "height": 14, "left": 320}, "words": "24个月"}, {"probability": {"variance": 9.2e-05, "average": 0.996182, "min": 0.964678}, "location": {"width": 124, "top": 561, "height": 14, "left": 426}, "words": "《中国药典》2015年版"}, {"probability": {"variance": 0.001089, "average": 0.980226, "min": 0.869716}, "location": {"width": 111, "top": 561, "height": 13, "left": 591}, "words": "国药佳字H20054022"}, {"probability": {"variance": 0.00116, "average": 0.986726, "min": 0.860447}, "location": {"width": 182, "top": 598, "height": 16, "left": 32}, "words": "聚丙烯共混输液袋装,每袋250m"}, {"probability": {"variance": 1e-06, "average": 0.998547, "min": 0.997098}, "location": {"width": 35, "top": 605, "height": 14, "left": 324}, "words": "24个月"}, {"probability": {"variance": 1e-06, "average": 0.99899, "min": 0.996553}, "location": {"width": 124, "top": 605, "height": 14, "left": 426}, "words": "《中国药典》2015年版"}, {"probability": {"variance": 0.019068, "average": 0.956213, "min": 0.477987}, "location": {"width": 112, "top": 605, "height": 14, "left": 591}, "words": "国药准字H20054022"}, {"probability": {"variance": 0.001509, "average": 0.983358, "min": 0.828862}, "location": {"width": 235, "top": 614, "height": 15, "left": 32}, "words": "聚丙烯共混输液袋装《双阀),每袋250ml"}, {"probability": {"variance": 0.000398, "average": 0.986992, "min": 0.945305}, "location": {"width": 62, "top": 652, "height": 16, "left": 26}, "words": "[生产企业]"}, {"probability": {"variance": 0.001989, "average": 0.983282, "min": 0.820369}, "location": {"width": 209, "top": 668, "height": 16, "left": 23}, "words": "企业名称:辽宁民康制药有限公司"}, {"probability": {"variance": 8.9e-05, "average": 0.996243, "min": 0.957252}, "location": {"width": 256, "top": 685, "height": 16, "left": 24}, "words": "生产地址:大连炮台经济开发区光彩街1号"}, {"probability": {"variance": 3.7e-05, "average": 0.994836, "min": 0.978292}, "location": {"width": 120, "top": 703, "height": 15, "left": 24}, "words": "邮政编码:116308"}, {"probability": {"variance": 0.000669, "average": 0.988879, "min": 0.905396}, "location": {"width": 182, "top": 720, "height": 15, "left": 23}, "words": "电话号码:(0411)85251072"}, {"probability": {"variance": 0.017368, "average": 0.957768, "min": 0.423134}, "location": {"width": 182, "top": 719, "height": 16, "left": 249}, "words": "传真号码:0411)66516128"}, {"probability": {"variance": 0.003905, "average": 0.944746, "min": 0.763556}, "location": {"width": 176, "top": 738, "height": 14, "left": 22}, "words": "网址:www. kelun.com"}, {"probability": {"variance": 0.021282, "average": 0.853484, "min": 0.685805}, "location": {"width": 295, "top": 926, "height": 76, "left": 428}, "words": "白价专用"}], "language": 3}