{"log_id": 8307409418052068444, "direction": 0, "words_result_num": 41, "words_result": [{"probability": {"variance": 0.025343, "average": 0.909905, "min": 0.427466}, "location": {"width": 639, "top": 267, "height": 36, "left": 271}, "words": "万缺用药网应定时或连续监测心电图、血压、心量必要或可能时监测"}, {"probability": {"variance": 0, "average": 0.997048, "min": 0.997048}, "location": {"width": 71, "top": 294, "height": 24, "left": 271}, "words": "压"}, {"probability": {"variance": 0.016984, "average": 0.924035, "min": 0.466939}, "location": {"width": 637, "top": 323, "height": 39, "left": 272}, "words": "给药说明:用药前应先补充容量、纠正血容量。药液的浓度随用和病人所液体"}, {"probability": {"variance": 0.016388, "average": 0.917333, "min": 0.558012}, "location": {"width": 635, "top": 352, "height": 38, "left": 276}, "words": "黛百定。疗时网和给药速度按病人的治疗效应调整,可依据心察、压、尿量以及"}, {"probability": {"variance": 0.016702, "average": 0.923183, "min": 0.445062}, "location": {"width": 601, "top": 379, "height": 40, "left": 278}, "words": "否出现异位动等情况。如有可能,应监测中心静脉压、肺楔嵌压和心拌血量"}, {"probability": {"variance": 0.036954, "average": 0.862909, "min": 0.392277}, "location": {"width": 248, "top": 408, "height": 30, "left": 290}, "words": "孕妇及游乳期妇女用药尚不明袋"}, {"probability": {"variance": 0.017673, "average": 0.931675, "min": 0.485472}, "location": {"width": 294, "top": 434, "height": 34, "left": 286}, "words": "儿用药1本品在小儿应用中缺乏研究"}, {"probability": {"variance": 0.019581, "average": 0.911983, "min": 0.39119}, "location": {"width": 447, "top": 464, "height": 35, "left": 286}, "words": "老年用药】在老年人中研究未进行,但应用预期不受限制"}, {"probability": {"variance": 0.011276, "average": 0.902307, "min": 0.652547}, "location": {"width": 133, "top": 493, "height": 25, "left": 274}, "words": "【药钢相作用】"}, {"probability": {"variance": 0.024265, "average": 0.87985, "min": 0.509522}, "location": {"width": 532, "top": 520, "height": 39, "left": 281}, "words": "1与全麻龙其丙烧、烷等同用,室性心掉失常发生的可能性增加"}, {"probability": {"variance": 0.046286, "average": 0.876271, "min": 0.372677}, "location": {"width": 632, "top": 550, "height": 39, "left": 281}, "words": "与受体阻剂同用,可插抗本品对,受体的作用,导致a受体作用占优势,外"}, {"probability": {"variance": 0.044122, "average": 0.826999, "min": 0.414985}, "location": {"width": 157, "top": 580, "height": 29, "left": 277}, "words": "血督的总阻力大"}, {"probability": {"variance": 0.036377, "average": 0.82693, "min": 0.446638}, "location": {"width": 411, "top": 609, "height": 36, "left": 279}, "words": ")与硝钠岗用,可学致心排斑量微增,肺嵌压略降"}, {"probability": {"variance": 0.005551, "average": 0.953963, "min": 0.74041}, "location": {"width": 324, "top": 637, "height": 35, "left": 283}, "words": "0本品不与碳氢钠碱性药物混合使用"}, {"probability": {"variance": 0.03254, "average": 0.886, "min": 0.426821}, "location": {"width": 350, "top": 666, "height": 34, "left": 279}, "words": "【药物过】进行该项实验无可靠参考文"}, {"probability": {"variance": 0.057381, "average": 0.85511, "min": 0.378502}, "location": {"width": 94, "top": 697, "height": 20, "left": 279}, "words": "【药理】"}, {"probability": {"variance": 0.029438, "average": 0.885511, "min": 0.41422}, "location": {"width": 597, "top": 722, "height": 38, "left": 284}, "words": "(对心产生正性繁力作用,生要作用于β,受体、对β及a受体作用相对较小"}, {"probability": {"variance": 0.021683, "average": 0.908299, "min": 0.500147}, "location": {"width": 558, "top": 752, "height": 36, "left": 283}, "words": "()能直接动心β,受体增强心肌收缩和增加排出量,使心排血量增加"}, {"probability": {"variance": 0.019264, "average": 0.921121, "min": 0.383699}, "location": {"width": 632, "top": 781, "height": 40, "left": 283}, "words": "3)可降低外周血管阻力(后负减少),但收缩压和脉压一般保持不变。或仅因心排"}, {"probability": {"variance": 0.048312, "average": 0.844031, "min": 0.440997}, "location": {"width": 139, "top": 809, "height": 25, "left": 285}, "words": "量雄加而有所增加"}, {"probability": {"variance": 0.027761, "average": 0.872113, "min": 0.412887}, "location": {"width": 282, "top": 837, "height": 31, "left": 292}, "words": ")能降低心室充盈压,促房室结传导"}, {"probability": {"variance": 0.00996, "average": 0.94925, "min": 0.657312}, "location": {"width": 443, "top": 866, "height": 37, "left": 289}, "words": ")心肌收缩力有所增强,冠状动脉血流及心肌耗氧盘常增加"}, {"probability": {"variance": 0.026868, "average": 0.873962, "min": 0.418435}, "location": {"width": 343, "top": 894, "height": 35, "left": 285}, "words": "由于心血增加,肾血流量及民量常增加"}, {"probability": {"variance": 0.027011, "average": 0.922412, "min": 0.377331}, "location": {"width": 632, "top": 920, "height": 47, "left": 290}, "words": "本品与多巴技不同,多巴干并不间接通过内源性去甲肾上腺素的释放,而是直"}, {"probability": {"variance": 0.000121, "average": 0.991556, "min": 0.967604}, "location": {"width": 106, "top": 952, "height": 23, "left": 288}, "words": "接作用于心脏"}, {"probability": {"variance": 0.026436, "average": 0.920359, "min": 0.370761}, "location": {"width": 608, "top": 979, "height": 41, "left": 286}, "words": "【药代动力学】口,注入一2分钟内起效,如缓慢滴注可延长到10分钟"}, {"probability": {"variance": 0.032208, "average": 0.886678, "min": 0.382873}, "location": {"width": 632, "top": 1008, "height": 40, "left": 289}, "words": "般注后10分钟作达鞋,续分钟,表观分布容积为0.21/kg,清除率为211L"}, {"probability": {"variance": 0.034675, "average": 0.844239, "min": 0.434145}, "location": {"width": 135, "top": 1038, "height": 21, "left": 301}, "words": "小时,半衰约为"}, {"probability": {"variance": 0.022247, "average": 0.934215, "min": 0.426175}, "location": {"width": 349, "top": 1045, "height": 29, "left": 558}, "words": "成无活性的化合物。代谢物主要经肾出"}, {"probability": {"variance": 0.055438, "average": 0.865853, "min": 0.395614}, "location": {"width": 104, "top": 1066, "height": 22, "left": 287}, "words": "【贮】光"}, {"probability": {"variance": 0, "average": 0.812204, "min": 0.812204}, "location": {"width": 192, "top": 1090, "height": 31, "left": 312}, "words": "】"}, {"probability": {"variance": 0.000488, "average": 0.981644, "min": 0.939569}, "location": {"width": 100, "top": 1123, "height": 22, "left": 301}, "words": "有效期】24个"}, {"probability": {"variance": 0.041005, "average": 0.862933, "min": 0.372103}, "location": {"width": 175, "top": 1150, "height": 25, "left": 293}, "words": "【执行准《中国"}, {"probability": {"variance": 0.002072, "average": 0.970157, "min": 0.875346}, "location": {"width": 139, "top": 1178, "height": 23, "left": 300}, "words": "批准文国药准"}, {"probability": {"variance": 0.001278, "average": 0.979286, "min": 0.908164}, "location": {"width": 91, "top": 1194, "height": 30, "left": 294}, "words": "【生企业】"}, {"probability": {"variance": 0.007055, "average": 0.939428, "min": 0.752899}, "location": {"width": 141, "top": 1233, "height": 25, "left": 443}, "words": "化药业有限公司"}, {"probability": {"variance": 0, "average": 0.99734, "min": 0.99734}, "location": {"width": 38, "top": 1259, "height": 21, "left": 309}, "words": "地"}, {"probability": {"variance": 0.028485, "average": 0.914244, "min": 0.482024}, "location": {"width": 139, "top": 1288, "height": 21, "left": 297}, "words": "紹政编码:200240"}, {"probability": {"variance": 0.018071, "average": 0.929735, "min": 0.537219}, "location": {"width": 195, "top": 1312, "height": 30, "left": 294}, "words": "电话号码:031-6430059"}, {"probability": {"variance": 0.051574, "average": 0.850893, "min": 0.377266}, "location": {"width": 106, "top": 1343, "height": 21, "left": 297}, "words": "传号码:02"}, {"probability": {"variance": 2e-06, "average": 0.995512, "min": 0.994219}, "location": {"width": 40, "top": 1371, "height": 18, "left": 298}, "words": "网址"}], "language": 3}