{"log_id": 573834435174026421, "direction": 0, "words_result_num": 36, "words_result": [{"probability": {"variance": 0.065484, "average": 0.812736, "min": 0.393606}, "location": {"width": 134, "top": 22, "height": 27, "left": 315}, "words": "日期:20"}, {"probability": {"variance": 0.004621, "average": 0.974591, "min": 0.701857}, "location": {"width": 890, "top": 141, "height": 68, "left": 383}, "words": "单唾液酸四已糖神经节苷脂钠盐注射液说明书"}, {"probability": {"variance": 0.004644, "average": 0.962806, "min": 0.760971}, "location": {"width": 383, "top": 216, "height": 34, "left": 639}, "words": "请仔细阅读说明书并在医师指导下使用"}, {"probability": {"variance": 0.035555, "average": 0.86705, "min": 0.390128}, "location": {"width": 559, "top": 253, "height": 38, "left": 550}, "words": "凭医师处方销售、购买和使用。妥善存放,避免儿接触"}, {"probability": {"variance": 5.8e-05, "average": 0.990497, "min": 0.977805}, "location": {"width": 134, "top": 317, "height": 31, "left": 310}, "words": "【药品名称"}, {"probability": {"variance": 0.033247, "average": 0.846255, "min": 0.471613}, "location": {"width": 520, "top": 349, "height": 36, "left": 317}, "words": "通用名称:直师液酸四已神经声磨纳盐注射液"}, {"probability": {"variance": 0.043137, "average": 0.824278, "min": 0.396363}, "location": {"width": 189, "top": 397, "height": 29, "left": 317}, "words": "品名称:施捷因"}, {"probability": {"variance": 0.01796, "average": 0.902636, "min": 0.6738}, "location": {"width": 143, "top": 438, "height": 27, "left": 317}, "words": "英文名称;M"}, {"probability": {"variance": 0, "average": 0.285389, "min": 0.285389}, "location": {"width": 22, "top": 443, "height": 20, "left": 628}, "words": " 191"}, {"probability": {"variance": 0.05484, "average": 0.738943, "min": 0.413391}, "location": {"width": 111, "top": 433, "height": 22, "left": 829}, "words": " m Salt Inc"}, {"probability": {"variance": 0.04774, "average": 0.79739, "min": 0.376283}, "location": {"width": 141, "top": 477, "height": 27, "left": 319}, "words": "汉沿拼:D"}, {"probability": {"variance": 0.03523, "average": 0.725903, "min": 0.472297}, "location": {"width": 148, "top": 472, "height": 27, "left": 756}, "words": " Hing jie gun h"}, {"probability": {"variance": 0.064242, "average": 0.823973, "min": 0.386355}, "location": {"width": 86, "top": 516, "height": 27, "left": 315}, "words": "【份】"}, {"probability": {"variance": 0.063694, "average": 0.753241, "min": 0.36917}, "location": {"width": 404, "top": 545, "height": 36, "left": 319}, "words": "化学名称单被二神经节脂"}, {"probability": {"variance": 0.0243, "average": 0.896108, "min": 0.567618}, "location": {"width": 123, "top": 591, "height": 29, "left": 324}, "words": "化学结构式:"}, {"probability": {"variance": 0.0232, "average": 0.836383, "min": 0.601815}, "location": {"width": 148, "top": 870, "height": 25, "left": 319}, "words": "分子式;C1I1"}, {"probability": {"variance": 7e-06, "average": 0.993907, "min": 0.990511}, "location": {"width": 77, "top": 906, "height": 27, "left": 317}, "words": "分子量"}, {"probability": {"variance": 0, "average": 0.886621, "min": 0.886621}, "location": {"width": 54, "top": 945, "height": 27, "left": 317}, "words": "组"}, {"probability": {"variance": 0.035423, "average": 0.803272, "min": 0.447542}, "location": {"width": 114, "top": 982, "height": 27, "left": 429}, "words": "支,每支宫"}, {"probability": {"variance": 0.03855, "average": 0.834124, "min": 0.387469}, "location": {"width": 427, "top": 1016, "height": 34, "left": 317}, "words": "活性份:单液酸四已神经节苷脂讷"}, {"probability": {"variance": 0, "average": 0.907181, "min": 0.907181}, "location": {"width": 50, "top": 1062, "height": 27, "left": 322}, "words": "料"}, {"probability": {"variance": 0.02992, "average": 0.839664, "min": 0.436689}, "location": {"width": 212, "top": 1057, "height": 27, "left": 479}, "words": "碱价磷酸钠-12H2"}, {"probability": {"variance": 0.032203, "average": 0.821867, "min": 0.493661}, "location": {"width": 205, "top": 1098, "height": 27, "left": 477}, "words": "碱价磷酸钠-2H10"}, {"probability": {"variance": 0.040126, "average": 0.720371, "min": 0.537101}, "location": {"width": 73, "top": 1135, "height": 29, "left": 452}, "words": "氯化钠"}, {"probability": {"variance": 0.030286, "average": 0.886188, "min": 0.543608}, "location": {"width": 137, "top": 1176, "height": 27, "left": 452}, "words": "注射用水加"}, {"probability": {"variance": 0.002057, "average": 0.944447, "min": 0.899096}, "location": {"width": 22, "top": 1231, "height": 22, "left": 328}, "words": "10"}, {"probability": {"variance": 0.012922, "average": 0.934001, "min": 0.707042}, "location": {"width": 121, "top": 1224, "height": 29, "left": 445}, "words": "瓶,每瓶含"}, {"probability": {"variance": 0.009739, "average": 0.927747, "min": 0.653366}, "location": {"width": 422, "top": 1260, "height": 34, "left": 324}, "words": "活性成份:单唾液酸四己糖神经节脂"}, {"probability": {"variance": 0.039297, "average": 0.795995, "min": 0.59776}, "location": {"width": 54, "top": 1304, "height": 29, "left": 324}, "words": "辅料"}, {"probability": {"variance": 0.023126, "average": 0.902949, "min": 0.511695}, "location": {"width": 214, "top": 1299, "height": 29, "left": 479}, "words": "碱价璘酸钠-12H20"}, {"probability": {"variance": 0.045586, "average": 0.829741, "min": 0.400066}, "location": {"width": 201, "top": 1340, "height": 27, "left": 479}, "words": "碱价酸钠-2H20"}, {"probability": {"variance": 2.3e-05, "average": 0.996216, "min": 0.989382}, "location": {"width": 73, "top": 1379, "height": 27, "left": 461}, "words": "氯化钠"}, {"probability": {"variance": 0.004337, "average": 0.964411, "min": 0.817228}, "location": {"width": 141, "top": 1416, "height": 29, "left": 461}, "words": "注射用水加至"}, {"probability": {"variance": 0.017489, "average": 0.942897, "min": 0.425057}, "location": {"width": 413, "top": 1459, "height": 38, "left": 342}, "words": "【性扶】本品为无色或黄色的澄明液体"}, {"probability": {"variance": 0.035349, "average": 0.886901, "min": 0.396368}, "location": {"width": 566, "top": 1498, "height": 38, "left": 354}, "words": "适成症】血管性或外性中枢神经系统损伤:帕金森病"}, {"probability": {"variance": 0.037396, "average": 0.800615, "min": 0.406939}, "location": {"width": 232, "top": 1541, "height": 29, "left": 340}, "words": "规格】20mg/2mm支"}], "language": 3}