{"log_id": 1674945475666399137, "direction": 0, "words_result_num": 33, "words_result": [{"probability": {"variance": 3.6e-05, "average": 0.997507, "min": 0.974682}, "location": {"width": 770, "top": 158, "height": 30, "left": 255}, "words": "多剂量给药毒性:对大鼠和家兔给予总剂量为20mg/kg铁的多剂量研究发现"}, {"probability": {"variance": 1e-06, "average": 0.998993, "min": 0.995354}, "location": {"width": 827, "top": 198, "height": 31, "left": 210}, "words": "在低剂量组中无显著的损伤出现,在大鼠的高剂量组中与对照组相比,大鼠体重"}, {"probability": {"variance": 3.6e-05, "average": 0.996958, "min": 0.976799}, "location": {"width": 824, "top": 237, "height": 33, "left": 211}, "words": "有所增加,肝脏出现肿大,但未导致肝功能的损伤。给年龄10个月的 Beagle"}, {"probability": {"variance": 8e-06, "average": 0.998316, "min": 0.986367}, "location": {"width": 826, "top": 277, "height": 35, "left": 210}, "words": "狗每周2次每次相当于50mg/kg铁的右旋糖酐铁,共持续5周,结果显示,对肝"}, {"probability": {"variance": 4.5e-05, "average": 0.996677, "min": 0.968298}, "location": {"width": 826, "top": 319, "height": 31, "left": 211}, "words": "脏的影响与其他动物相似,但在巩膜出现色斑。对 Sprague- Dawley小鼠短期给"}, {"probability": {"variance": 1e-06, "average": 0.998919, "min": 0.995185}, "location": {"width": 813, "top": 358, "height": 36, "left": 213}, "words": "予大剂量右旋糖酐铁(100mg/kg铁共7天),对动物肝脏进行解剖组织学研究"}, {"probability": {"variance": 2.6e-05, "average": 0.998025, "min": 0.969284}, "location": {"width": 826, "top": 401, "height": 30, "left": 211}, "words": "发现在肝细胞中出现铁的沉积,但未见对肝细胞的损害。肝细胞中铁的浓度有明"}, {"probability": {"variance": 3e-06, "average": 0.998617, "min": 0.992563}, "location": {"width": 623, "top": 442, "height": 30, "left": 212}, "words": "显增加与肝细胞中脂类过氧化物和聚胺氧化酶活性增加有关"}, {"probability": {"variance": 2e-06, "average": 0.999034, "min": 0.992898}, "location": {"width": 692, "top": 494, "height": 30, "left": 254}, "words": "无证据表明本品对生殖能力有毒性作用、致畸、致突变和致癌作用"}, {"probability": {"variance": 2e-05, "average": 0.997615, "min": 0.986739}, "location": {"width": 153, "top": 549, "height": 28, "left": 219}, "words": "【药代动力学】"}, {"probability": {"variance": 9e-06, "average": 0.998536, "min": 0.983043}, "location": {"width": 779, "top": 599, "height": 31, "left": 258}, "words": "右旋糖酐铁静脉滴注后,能被网状内皮系统细胞摄取,特别是在肝脏和脾脏"}, {"probability": {"variance": 7e-06, "average": 0.998626, "min": 0.988982}, "location": {"width": 817, "top": 640, "height": 29, "left": 212}, "words": "中。铁能缓慢地释放并结合于蛋白。6~8周后可观察到造血功能增强。循环铁"}, {"probability": {"variance": 2e-06, "average": 0.99901, "min": 0.99495}, "location": {"width": 704, "top": 678, "height": 31, "left": 211}, "words": "的血浆半衰期为5小时,总铁(结合的和循环的)半衰期为20小时"}, {"probability": {"variance": 1e-06, "average": 0.999386, "min": 0.994498}, "location": {"width": 766, "top": 731, "height": 33, "left": 265}, "words": "肌内注射后,右旋糖酐铁从注射部位被吸收入毛细血管和淋巴系统。循环"}, {"probability": {"variance": 1e-06, "average": 0.999244, "min": 0.996562}, "location": {"width": 830, "top": 773, "height": 29, "left": 211}, "words": "铁被网状内皮系统细胞吞噬,将分解成铁和右旋糖酐。铁能立即与蛋白结合形成"}, {"probability": {"variance": 1.6e-05, "average": 0.997875, "min": 0.979787}, "location": {"width": 826, "top": 812, "height": 30, "left": 211}, "words": "血铁黄素或铁蛋白,还有少部分形成转铁蛋白。这种铁在生理调节下可补充血红"}, {"probability": {"variance": 0, "average": 0.999467, "min": 0.99875}, "location": {"width": 193, "top": 855, "height": 27, "left": 211}, "words": "蛋白和消耗铁储备"}, {"probability": {"variance": 1e-06, "average": 0.999249, "min": 0.99511}, "location": {"width": 773, "top": 905, "height": 30, "left": 267}, "words": "肌内注射右旋糖酐铁,大部分在72小时内被吸收,大多数剩余的铁在随后"}, {"probability": {"variance": 1e-06, "average": 0.999277, "min": 0.99671}, "location": {"width": 181, "top": 948, "height": 27, "left": 211}, "words": "的3~4周被吸收"}, {"probability": {"variance": 2e-06, "average": 0.999002, "min": 0.993644}, "location": {"width": 718, "top": 996, "height": 30, "left": 260}, "words": "铁不易从机体中被清除,过量蓄积可能会有毒性。该复合物分子较大"}, {"probability": {"variance": 1.4e-05, "average": 0.998479, "min": 0.977495}, "location": {"width": 824, "top": 1038, "height": 29, "left": 215}, "words": "(65,000Da),不易通过肾清除。少量的铁能通过尿液和粪便清除。右旋糖酐可"}, {"probability": {"variance": 0, "average": 0.999356, "min": 0.99786}, "location": {"width": 171, "top": 1080, "height": 28, "left": 211}, "words": "以被代谢和消除"}, {"probability": {"variance": 1e-06, "average": 0.999213, "min": 0.996071}, "location": {"width": 709, "top": 1131, "height": 29, "left": 221}, "words": "【贮藏】室温(10~30℃)保存,药物应置儿童不能触及的地方"}, {"probability": {"variance": 0.004311, "average": 0.984259, "min": 0.663068}, "location": {"width": 576, "top": 1185, "height": 28, "left": 218}, "words": "【包装】棕色中性玻璃安瓿,2ml/安瓿,5安瓿/盒"}, {"probability": {"variance": 1.3e-05, "average": 0.997195, "min": 0.988376}, "location": {"width": 239, "top": 1239, "height": 29, "left": 220}, "words": "【有效期】36个月"}, {"probability": {"variance": 0.001088, "average": 0.984981, "min": 0.884665}, "location": {"width": 508, "top": 1290, "height": 30, "left": 218}, "words": "【执行标准】进口药品注册标准JX20070210"}, {"probability": {"variance": 0.003575, "average": 0.982249, "min": 0.703282}, "location": {"width": 492, "top": 1342, "height": 30, "left": 220}, "words": "【批准文号】进口药品注册证号H20080311"}, {"probability": {"variance": 1e-06, "average": 0.999119, "min": 0.996939}, "location": {"width": 130, "top": 1396, "height": 28, "left": 220}, "words": "【生产企业】"}, {"probability": {"variance": 0.000754, "average": 0.96901, "min": 0.933026}, "location": {"width": 163, "top": 1386, "height": 67, "left": 729}, "words": "限公司"}, {"probability": {"variance": 4.9e-05, "average": 0.996317, "min": 0.980868}, "location": {"width": 138, "top": 1450, "height": 28, "left": 254}, "words": "企业名称:P"}, {"probability": {"variance": 0.008834, "average": 0.928005, "min": 0.766914}, "location": {"width": 148, "top": 1452, "height": 23, "left": 528}, "words": " a/s, Denmark"}, {"probability": {"variance": 0, "average": 0.712923, "min": 0.712923}, "location": {"width": 43, "top": 1446, "height": 40, "left": 712}, "words": "必"}, {"probability": {"variance": 0.003059, "average": 0.970992, "min": 0.775021}, "location": {"width": 497, "top": 1503, "height": 27, "left": 256}, "words": "生产地址: Roervangsve j30Dk-4300 Holbaek,"}], "language": 3}